ionq_direct/__init__.py
ionq_direct/ionq_direct.py
ionq_direct-0.0.2.dist-info/METADATA
ionq_direct-0.0.2.dist-info/WHEEL
ionq_direct-0.0.2.dist-info/top_level.txt
ionq_direct-0.0.2.dist-info/RECORD
