Metadata-Version: 2.1
Name: ionq-direct
Version: 0.0.2
Summary: IonQ QPU Batch Submission package via Pennylane
Author: Dhruv Srinivasan
Author-email: <dhruvs@terpmail.umd.edu>
Keywords: python,quantum,pennylane,IonQ,noisy,circuits
Classifier: Development Status :: 3 - Alpha
Classifier: Intended Audience :: Science/Research
Classifier: Programming Language :: Python :: 3
Requires-Dist: pennylane
Requires-Dist: ionizer
